hypersquirrel/__init__.py
hypersquirrel/__main__.py
hypersquirrel/core.py
hypersquirrel/entry.py
hypersquirrel/literalinterpreterfactory.py
hypersquirrel/scraperfactory.py
hypersquirrel/util.py
hypersquirrel/literalinterpreter/__init__.py
hypersquirrel/literalinterpreter/ehen.py
hypersquirrel/literalinterpreter/instagram.py
hypersquirrel/literalinterpreter/ph.py
hypersquirrel/scraper/__init__.py
hypersquirrel/scraper/buondua.py
hypersquirrel/scraper/cosplayporntube.py
hypersquirrel/scraper/drts.py
hypersquirrel/scraper/ehen.py
hypersquirrel/scraper/fseg.py
hypersquirrel/scraper/googleimagesearch.py
hypersquirrel/scraper/hcos.py
hypersquirrel/scraper/hellp.py
hypersquirrel/scraper/hnlg.py
hypersquirrel/scraper/incflix.py
hypersquirrel/scraper/lgbb.py
hypersquirrel/scraper/nh.py
hypersquirrel/scraper/nlgs.py
hypersquirrel/scraper/opendir.py
hypersquirrel/scraper/reddit.py
hypersquirrel/scraper/sb.py
hypersquirrel/scraper/sbgx.py
hypersquirrel/scraper/v2ph.py
hypersquirrel/scraper/vg.py
hypersquirrel/scraper/xh.py
hypersquirrel/scraper/xv.py
hypersquirrel/scraper/youtubeapi.py
ytdlwrapper/__init__.py
ytdlwrapper/ytdlpscrape.py
hypersquirrel-1.0.38.dist-info/LICENSE
hypersquirrel-1.0.38.dist-info/METADATA
hypersquirrel-1.0.38.dist-info/WHEEL
hypersquirrel-1.0.38.dist-info/top_level.txt
hypersquirrel-1.0.38.dist-info/RECORD
