Metadata-Version: 2.1
Name: hypersquirrel
Version: 1.0.38
Summary: Scrapes posts from various websites
Home-page: UNKNOWN
Author: vka
License: UNKNOWN
Platform: UNKNOWN
Classifier: Programming Language :: Python :: 3
Classifier: Operating System :: OS Independent
Requires-Python: >=3.6
License-File: LICENSE
Requires-Dist: requests
Requires-Dist: vripper
Requires-Dist: htmllistparse
Requires-Dist: commmons
Requires-Dist: feedparser
